mobilerun/__init__.py
mobilerun/_base_client.py
mobilerun/_client.py
mobilerun/_compat.py
mobilerun/_constants.py
mobilerun/_exceptions.py
mobilerun/_files.py
mobilerun/_models.py
mobilerun/_qs.py
mobilerun/_resource.py
mobilerun/_response.py
mobilerun/_streaming.py
mobilerun/_types.py
mobilerun/_version.py
mobilerun/py.typed
mobilerun/_utils/__init__.py
mobilerun/_utils/_compat.py
mobilerun/_utils/_datetime_parse.py
mobilerun/_utils/_logs.py
mobilerun/_utils/_proxy.py
mobilerun/_utils/_reflection.py
mobilerun/_utils/_resources_proxy.py
mobilerun/_utils/_streams.py
mobilerun/_utils/_sync.py
mobilerun/_utils/_transform.py
mobilerun/_utils/_typing.py
mobilerun/_utils/_utils.py
mobilerun/lib/.keep
mobilerun/resources/__init__.py
mobilerun/resources/apps.py
mobilerun/resources/hooks.py
mobilerun/resources/credentials/__init__.py
mobilerun/resources/credentials/credentials.py
mobilerun/resources/credentials/packages/__init__.py
mobilerun/resources/credentials/packages/packages.py
mobilerun/resources/credentials/packages/credentials/__init__.py
mobilerun/resources/credentials/packages/credentials/credentials.py
mobilerun/resources/credentials/packages/credentials/fields.py
mobilerun/resources/devices/__init__.py
mobilerun/resources/devices/actions.py
mobilerun/resources/devices/apps.py
mobilerun/resources/devices/devices.py
mobilerun/resources/devices/keyboard.py
mobilerun/resources/devices/packages.py
mobilerun/resources/devices/state.py
mobilerun/resources/tasks/__init__.py
mobilerun/resources/tasks/screenshots.py
mobilerun/resources/tasks/tasks.py
mobilerun/resources/tasks/ui_states.py
mobilerun/types/__init__.py
mobilerun/types/app_list_params.py
mobilerun/types/app_list_response.py
mobilerun/types/credential_list_response.py
mobilerun/types/device.py
mobilerun/types/device_create_params.py
mobilerun/types/device_list_params.py
mobilerun/types/device_list_response.py
mobilerun/types/hook_get_sample_data_response.py
mobilerun/types/hook_list_params.py
mobilerun_sdk-0.1.0.dist-info/METADATA
mobilerun_sdk-0.1.0.dist-info/WHEEL
mobilerun_sdk-0.1.0.dist-info/licenses/LICENSE
mobilerun_sdk-0.1.0.dist-info/RECORD
